Metadata-Version: 2.1
Name: bocd
Version: 0.1.2
Summary: Bayesian online changepoint detection
Home-page: https://github.com/y-bar/bocd
Maintainer: Nagi Teramo
Maintainer-email: teramonagi@gmail.com
License: MIT
Platform: UNKNOWN
